{
  "query": "grotesque genitals",
  "timestamp": 1756802534055,
  "expiresAt": 1757407334055,
  "result": {
    "hits": [
      {
        "id": "815c862a-004c-40da-aaae-070203a692c9",
        "season": "s03",
        "time": "0:16:55",
        "speaker": "3",
        "line": "more devastating. It's just devastating. As you all know, we keep all the money that funds this school in a bottomless piggy bank that is a pig with its pants. Ceramic pig with his pants pulled to the ground, showcasing its grotesque genitals. Sorry, Imogene. Sort of ceramic genitals. It was designed by one of our best friends, Pablo Picasso,",
        "episode": "s03e05",
        "edited": false
      },
      {
        "id": "8a6d86cc-b725-4103-99a2-bcaf987b35f8",
        "season": "s03",
        "time": "0:17:59",
        "speaker": "3",
        "line": "currently keeping all of our money in cash in a bottomless piggy bank. And that is a big ceramic pig. Things got his band's mope with no bats and grotesque genitals. And it was, uh, designed and made by my one of my good friends Slob Low Picasso. That's right. That's right.",
        "episode": "s03e02",
        "edited": false
      },
      {
        "id": "5ee6fd97-48f4-4cd4-8a50-62d861fdd4ad",
        "season": "s03",
        "time": "0:18:08",
        "speaker": "2",
        "line": "bottomless piggy bank was our ceramic pig that had its pants pulled to its ankles. And ah, it's grotesque. Genitals were shown. It was beautifully crafted by our good friend slob Low Picasso, who is not related to the painter Picasso but instead related to Petey slob slob Blow the Southern",
        "episode": "s03e07",
        "edited": false
      },
      {
        "id": "bf5c4339-fc8f-466d-8071-47d54ef568fc",
        "season": "s03",
        "time": "0:21:29",
        "speaker": "2",
        "line": "a big pig ceramic pig that's got grotesques genitals, and it's got",
        "episode": "s03e01",
        "edited": false
      },
      {
        "id": "912b5d61-6856-4284-b70f-6fc220e21afd",
        "season": "s03",
        "time": "0:26:02",
        "speaker": "2",
        "line": "piggy bank. Huh? What? That's bottoms pulled to its ankles. Let's g o on. And you should see it's grotesque. Genitals are kind of splayed out on showing on. And it was done by our friends. Slob Low Picasso,",
        "episode": "s03e05",
        "edited": false
      },
      {
        "id": "1f207bc5-d75c-4ac6-b273-7fc3129a3694",
        "season": "s03",
        "time": "0:51:03",
        "speaker": "4",
        "line": "we go. We've got a bottomless piggy bank. You took a bullet to the ground and get grotesque tentacle genitals, and it's filled with cash. Don't you kids go looking",
        "episode": "s03e03",
        "edited": false
      }
    ],
    "stats": {
      "estimatedTotalHits": 6,
      "processingTime": 0,
      "facets": [
        {
          "facetName": "season",
          "facetHits": [
            {
              "ep": "s03",
              "hits": 6
            }
          ]
        },
        {
          "facetName": "episode",
          "facetHits": [
            {
              "ep": "s03e05",
              "hits": 2
            },
            {
              "ep": "s03e01",
              "hits": 1
            },
            {
              "ep": "s03e02",
              "hits": 1
            },
            {
              "ep": "s03e03",
              "hits": 1
            },
            {
              "ep": "s03e07",
              "hits": 1
            }
          ]
        }
      ]
    },
    "hasMore": false
  }
}